README.md
setup.py
lostdata/__init__.py
lostdata/__main__.py
lostdata/config.py
lostdata/formats.py
lostdata/processing.py
lostdata.egg-info/PKG-INFO
lostdata.egg-info/SOURCES.txt
lostdata.egg-info/dependency_links.txt
lostdata.egg-info/not-zip-safe
lostdata.egg-info/requires.txt
lostdata.egg-info/top_level.txt
lostdata/dealer/__init__.py
lostdata/dealer/cancer.py
lostdata/dealer/celllines.py
lostdata/dealer/cohorts.py
lostdata/dealer/drugging.py
lostdata/dealer/ensembl.py
lostdata/dealer/entrez.py
lostdata/dealer/genenames.py
lostdata/dealer/kegg.py
lostdata/dealer/mirbase.py
lostdata/dealer/networks.py
lostdata/dealer/sanger.py
lostdata/dealer/systems.py
lostdata/dealer/uniprot.py
lostdata/dealer/drugbanks/__init__.py
lostdata/dealer/genomes/__init__.py
lostdata/dealer/genomes/igsr.py
lostdata/dealer/home/__init__.py
lostdata/dealer/home/cnvdata.py
lostdata/dealer/home/models.py